bytedpilot/__init__.py
bytedpilot/__main__.py
bytedpilot/main.py
bytedpilot_0.0.15-1.0.1.dist-info/LICENSE
bytedpilot_0.0.15-1.0.1.dist-info/METADATA
bytedpilot_0.0.15-1.0.1.dist-info/WHEEL
bytedpilot_0.0.15-1.0.1.dist-info/top_level.txt
bytedpilot_0.0.15-1.0.1.dist-info/RECORD
